odoo/addons/shopinvader_customer_multi_user_company_group/README.rst
odoo/addons/shopinvader_customer_multi_user_company_group/__init__.py
odoo/addons/shopinvader_customer_multi_user_company_group/__manifest__.py
odoo/addons/shopinvader_customer_multi_user_company_group/i18n/shopinvader_customer_multi_user_company_group.pot
odoo/addons/shopinvader_customer_multi_user_company_group/migrations/14.0.2.0.0/post-migrate.py
odoo/addons/shopinvader_customer_multi_user_company_group/models/__init__.py
odoo/addons/shopinvader_customer_multi_user_company_group/models/shopinvader_backend.py
odoo/addons/shopinvader_customer_multi_user_company_group/models/shopinvader_partner.py
odoo/addons/shopinvader_customer_multi_user_company_group/readme/CONTRIBUTORS.rst
odoo/addons/shopinvader_customer_multi_user_company_group/readme/DESCRIPTION.rst
odoo/addons/shopinvader_customer_multi_user_company_group/static/description/index.html
odoo/addons/shopinvader_customer_multi_user_company_group/tests/__init__.py
odoo/addons/shopinvader_customer_multi_user_company_group/tests/common.py
odoo/addons/shopinvader_customer_multi_user_company_group/tests/test_multi_user_service_partner_domain.py
odoo/addons/shopinvader_customer_multi_user_company_group/views/shopinvader_backend.xml
odoo/addons/shopinvader_customer_multi_user_company_group/views/shopinvader_partner.xml
odoo14_addon_shopinvader_customer_multi_user_company_group-14.0.3.0.0.dist-info/METADATA
odoo14_addon_shopinvader_customer_multi_user_company_group-14.0.3.0.0.dist-info/WHEEL
odoo14_addon_shopinvader_customer_multi_user_company_group-14.0.3.0.0.dist-info/top_level.txt
odoo14_addon_shopinvader_customer_multi_user_company_group-14.0.3.0.0.dist-info/RECORD
