Metadata-Version: 2.1
Name: odoo14-addon-shopinvader-customer-multi-user-company-group
Version: 14.0.3.0.0
Summary: Share shopinvader records within the Company Group
Home-page: https://github.com/shopinvader/odoo-shopinvader
Author: Camptocamp SA
License: AGPL-3
Platform: UNKNOWN
Classifier: Programming Language :: Python
Classifier: Framework :: Odoo
Classifier: Framework :: Odoo :: 14.0
Classifier: License :: OSI Approved :: GNU Affero General Public License v3
Requires-Python: >=3.6
Requires-Dist: odoo14-addon-partner-company-group
Requires-Dist: odoo14-addon-shopinvader-customer-multi-user
Requires-Dist: odoo (<14.1dev,>=14.0a)
